LICENSE
MANIFEST.in
README.md
setup.py
tests/__init__.py
tests/http_response_catcher.py
tests/test_helper.py
tests/controllers/__init__.py
tests/controllers/controller_test_base.py
tests/controllers/test_api_controller.py
xbsryzmvon/__init__.py
xbsryzmvon/api_helper.py
xbsryzmvon/configuration.py
xbsryzmvon/decorators.py
xbsryzmvon/xbsryzmvon_client.py
xbsryzmvon.egg-info/PKG-INFO
xbsryzmvon.egg-info/SOURCES.txt
xbsryzmvon.egg-info/dependency_links.txt
xbsryzmvon.egg-info/requires.txt
xbsryzmvon.egg-info/top_level.txt
xbsryzmvon/controllers/__init__.py
xbsryzmvon/controllers/api_controller.py
xbsryzmvon/controllers/base_controller.py
xbsryzmvon/exceptions/__init__.py
xbsryzmvon/exceptions/api_exception.py
xbsryzmvon/http/__init__.py
xbsryzmvon/http/http_call_back.py
xbsryzmvon/http/http_client.py
xbsryzmvon/http/http_context.py
xbsryzmvon/http/http_method_enum.py
xbsryzmvon/http/http_request.py
xbsryzmvon/http/http_response.py
xbsryzmvon/http/requests_client.py
xbsryzmvon/http/auth/__init__.py
xbsryzmvon/http/auth/basic_auth.py
xbsryzmvon/models/__init__.py
xbsryzmvon/models/suite_code_enum.py